tpdf/__init__.py
tpdf/compiler.py
tpdf/document.py
tpdf/utils.py
tpdf-0.2.0.dist-info/licenses/LICENSE
tpdf-0.2.0.dist-info/METADATA
tpdf-0.2.0.dist-info/WHEEL
tpdf-0.2.0.dist-info/top_level.txt
tpdf-0.2.0.dist-info/RECORD
