Metadata-Version: 2.4
Name: tpdf
Version: 0.2.0
Summary: Text Portable Document Format - AI-friendly PDF generation
Home-page: https://github.com/thecoolrobot/tpdf
Author: Your Name
Author-email: Your Name <your.email@example.com>
License: MIT
Project-URL: Homepage, https://github.com/thecoolrobot/tpdf
Project-URL: Documentation, https://github.com/thecoolrobot/tpdf#readme
Project-URL: Repository, https://github.com/thecoolrobot/tpdf
Project-URL: Issues, https://github.com/thecoolrobot/tpdf/issues
Keywords: pdf,document,ai,generation
Classifier: Development Status :: 4 - Beta
Classifier: Intended Audience :: Developers
Classifier: Programming Language :: Python :: 3
Requires-Python: >=3.8
License-File: LICENSE
Requires-Dist: reportlab>=4.0.0
Requires-Dist: requests>=2.25.0
Provides-Extra: dev
Requires-Dist: pytest>=7.0; extra == "dev"
Requires-Dist: black>=22.0; extra == "dev"
Requires-Dist: flake8>=4.0; extra == "dev"
Dynamic: author
Dynamic: home-page
Dynamic: license-file
Dynamic: requires-python
